langdiversity/__init__.py
langdiversity/extras/__init__.py
langdiversity/extras/spinner.py
langdiversity/measures/__init__.py
langdiversity/measures/abstract_measure.py
langdiversity/measures/empirical_probability.py
langdiversity/measures/gini_impurity.py
langdiversity/measures/shannon_entropy.py
langdiversity/models/__init__.py
langdiversity/models/abstract_base_model.py
langdiversity/models/openai.py
langdiversity/parser/__init__.py
langdiversity/parser/answer_extractor.py
langdiversity/parser/number_extractor.py
langdiversity/utils/__init__.py
langdiversity/utils/calculate_measures.py
langdiversity/utils/diversity_measures.py
langdiversity/utils/prompt_selection.py
langdiversity-1.1.6.dist-info/LICENSE
langdiversity-1.1.6.dist-info/METADATA
langdiversity-1.1.6.dist-info/WHEEL
langdiversity-1.1.6.dist-info/top_level.txt
langdiversity-1.1.6.dist-info/RECORD
